hushbugger.py
hushbugger-0.0.1.dist-info/DESCRIPTION.rst
hushbugger-0.0.1.dist-info/METADATA
hushbugger-0.0.1.dist-info/RECORD
hushbugger-0.0.1.dist-info/WHEEL
hushbugger-0.0.1.dist-info/metadata.json
hushbugger-0.0.1.dist-info/top_level.txt
