Metadata-Version: 2.0
Name: hushbugger
Version: 0.0.1
Summary: A silent alternative to debugging
Home-page: https://github.com/HushBugger/hushbugger
Author: HushBugger
Author-email: hushbugger@posteo.net
License: ISC
Platform: UNKNOWN
Classifier: Programming Language :: Python
Classifier: Programming Language :: Python :: 2
Classifier: Programming Language :: Python :: 3
Classifier: Programming Language :: Python :: Implementation :: CPython
Classifier: License :: OSI Approved :: ISC License (ISCL)
